RTFDE/__init__.py
RTFDE/deencapsulate.py
RTFDE/exceptions.py
RTFDE/grammar.py
RTFDE/text_extraction.py
RTFDE/transformers.py
RTFDE/utils.py
RTFDE-0.1.1.dist-info/LICENSE
RTFDE-0.1.1.dist-info/METADATA
RTFDE-0.1.1.dist-info/WHEEL
RTFDE-0.1.1.dist-info/top_level.txt
RTFDE-0.1.1.dist-info/RECORD
