Metadata-Version: 2.1
Name: RTFDE
Version: 0.1.1
Summary: A library for extracting HTML content from RTF encapsulated HTML as commonly found in the exchange MSG email format.
Home-page: https://github.com/seamustuohy/RTFDE
Author: seamus tuohy
Author-email: code@seamustuohy.com
Classifier: Programming Language :: Python :: 3
Classifier: License :: OSI Approved :: GNU Lesser General Public License v3 (LGPLv3)
Classifier: Operating System :: OS Independent
Classifier: Topic :: Text Processing :: Markup :: HTML
Classifier: Intended Audience :: Developers
Classifier: Topic :: Text Processing :: Filters
Classifier: Topic :: Communications :: Email :: Filters
Requires-Python: >=3.8
License-File: LICENSE
Requires-Dist: lark==1.1.8
Requires-Dist: oletools>=0.56
Provides-Extra: msg-parse
Requires-Dist: extract_msg>=0.27; extra == "msg-parse"
Provides-Extra: dev
Requires-Dist: lxml>=4.6; extra == "dev"
Requires-Dist: mypy>=1.1.1; extra == "dev"
Requires-Dist: pdoc3>=0.10.0; extra == "dev"
Requires-Dist: coverage>=7.2.2; extra == "dev"
